[{"video_id":"6431459482437878018","title":"「蒙古文」感受非遗魅力 阿拉善“非遗日”活动亮点纷呈","description":"提示：点击上方\"阿拉善发布\"↑免费订阅本刊","keywords":"阿拉善","display_url":"https://ixigua.com/group/6431459482437878018/","source":"阿拉善发布","aothor":{"media_creator_id":6063930436,"media_name":"阿拉善发布","media_url":"https://www.cnblogs.com/c/user/6063930436/"}},{"video_id":"6574683525960696328","title":"青春非遗梦：非遗的传承和青春的梦想","description":"青春非遗梦：非遗的传承和青春的梦想","keywords":"非遗梦","display_url":"https://ixigua.com/group/6574683525960696328/","source":"爱看中国蓝","aothor":{"media_creator_id":68721103144,"media_name":"爱看中国蓝","media_url":"https://www.cnblogs.com/c/user/68721103144/"}},{"video_id":"6304230577360863746","title":"“非遗” 经典纪录 甘肃花儿","description":"","keywords":"甘肃花儿,”,“,非遗,","display_url":"https://ixigua.com/group/6304230577360863746/","source":"歌声飞舞","aothor":{"media_creator_id":6780481935,"media_name":"歌声飞舞","media_url":"https://www.cnblogs.com/c/user/6780481935/"}},{"video_id":"6566446657360101902","title":"感受铜仁非遗文化 “非遗进园林”系列活动举行","description":"感受铜仁非遗文化 “非遗进园林”系列活动举行MF","keywords":"文化,铜仁,非遗","display_url":"https://ixigua.com/group/6566446657360101902/","source":"荔枝新闻","aothor":{"media_creator_id":6976474883,"media_name":"荔枝新闻","media_url":"https://www.cnblogs.com/c/user/6976474883/"}},{"video_id":"6679396302528184840","title":"青春带你看我们河包的非遗，朴素的文化传承，传承朴素的农味。","description":"河包的非遗，霸气的肉龙，震撼的效果，朴素的文化传承，传承朴素的农味。","keywords":"文化,非遗","display_url":"https://ixigua.com/group/6679396302528184840/","source":"慢生活青春家","aothor":{"media_creator_id":53295917485,"media_name":"慢生活青春家","media_url":"https://www.cnblogs.com/c/user/53295917485/"}},{"video_id":"6679078310623838723","title":"多彩贵州文创园 非遗文化博物馆","description":"多彩贵州文创园，非遗文化博物馆一起来看看？","keywords":"文化博物馆,文创园,贵州,博物馆,多彩贵州","display_url":"https://ixigua.com/group/6679078310623838723/","source":"百姓关注","aothor":{"media_creator_id":6953955789,"media_name":"百姓关注","media_url":"https://www.cnblogs.com/c/user/6953955789/"}},{"video_id":"6326408325836996866","title":"南京启动“非遗复兴” 设计师对话非遗传承人","description":"","keywords":"启动,设计师,南京,传承人,非遗","display_url":"https://ixigua.com/group/6326408325836996866/","source":"荔枝新闻","aothor":{"media_creator_id":6976474883,"media_name":"荔枝新闻","media_url":"https://www.cnblogs.com/c/user/6976474883/"}},{"video_id":"6486923704067424782","title":"国家级非遗——苗族锦鸡舞","description":"国家级非遗——苗族锦鸡舞","keywords":"苗族锦鸡舞","display_url":"https://ixigua.com/group/6486923704067424782/","source":"健仔游行记","aothor":{"media_creator_id":62968698129,"media_name":"健仔游行记","media_url":"https://www.cnblogs.com/c/user/62968698129/"}},{"video_id":"6424251012646699521","title":"逛回民街，吃永兴坊 非遗路 永兴坊寻找非遗美食","description":"西安，古称长安、镐京，陕西省省会、副省级市、国家区域中心城市（西北），是国务院批复确定的中国西部地区重要的中心城市，国家重要的科研、教育和工业基地，联合国科教文组织1981年确定的“世界历史名城” ，美媒评选的世界十大古都之一","keywords":"世界历史,副省级市,陕西省,永兴坊,回民街","display_url":"https://ixigua.com/group/6424251012646699521/","source":"旅途久久","aothor":{"media_creator_id":6677310301,"media_name":"旅途久久","media_url":"https://www.cnblogs.com/c/user/6677310301/"}},{"video_id":"6679673511792869901","title":"号外！济南动物园首届非遗文化启幕，可爱动物遇上传统技艺！","description":"号外！济南动物园首届非遗文化启幕，可爱动物遇上传统技艺！","keywords":"可爱动物,济南动物园,文化","display_url":"https://ixigua.com/group/6679673511792869901/","source":"济南广播电视台","aothor":{"media_creator_id":83924053476,"media_name":"济南广播电视台","media_url":"https://www.cnblogs.com/c/user/83924053476/"}},{"video_id":"6460639781540856334","title":"非遗自救“活”起来","description":"","keywords":"","display_url":"https://ixigua.com/group/6460639781540856334/","source":"荔枝新闻","aothor":{"media_creator_id":6976474883,"media_name":"荔枝新闻","media_url":"https://www.cnblogs.com/c/user/6976474883/"}},{"video_id":"6396219150394425601","title":"致力非遗：你我一起行动（中央电视台非遗公益宣传片）","description":"生活中很多东西都在流逝，我们能做的就是为非遗传承贡献自己的力量","keywords":"","display_url":"https://ixigua.com/group/6396219150394425601/","source":"贰零2019壹玖","aothor":{"media_creator_id":1821295262,"media_name":"贰零2019壹玖","media_url":"https://www.cnblogs.com/c/user/1821295262/"}},{"video_id":"6679681537039925767","title":"济南动物园首届非遗文化节开幕！竹编，皮影，糖画都有，持续21天","description":"济南动物园首届非遗文化节开幕了！竹编，皮影，糖画都有，持续21天！","keywords":"皮影,糖画,济南动物园,竹编,文化节","display_url":"https://ixigua.com/group/6679681537039925767/","source":"济南广播电视台","aothor":{"media_creator_id":83924053476,"media_name":"济南广播电视台","media_url":"https://www.cnblogs.com/c/user/83924053476/"}},{"video_id":"6298853848668701186","title":"非遗精品展示 提升非遗关注度","description":"非遗精品展示 提升非遗关注度","keywords":"非遗","display_url":"https://stream4.iqilu.com/vod_bag_2016//2016/06/22/FF2F968D309A4376971777C6F6EA3618/FF2F968D309A4376971777C6F6EA3618_H264_mp4_500K.mp4","source":"齐鲁网","aothor":{"media_creator_id":3405414616,"media_name":"齐鲁网","media_url":"https://www.cnblogs.com/c/user/3405414616/"}},{"video_id":"6679231208754250253","title":"太原市非遗文旅小镇挂牌成立，已入驻21个项目","description":"太原市非遗文旅小镇挂牌成立，已入驻21个项目LT","keywords":"小镇,太原市","display_url":"https://ixigua.com/group/6679231208754250253/","source":"都市110","aothor":{"media_creator_id":5899163587,"media_name":"都市110","media_url":"https://www.cnblogs.com/c/user/5899163587/"}},{"video_id":"6652300003555410440","title":"东营非遗快闪《鼓舞济南路》，非遗时尚派来袭","description":"东营区文化和旅游局出品，非遗快闪《鼓舞济南路》，非遗也能完成时尚感！","keywords":"鼓舞济南路,东营,时尚派,旅游局,非遗","display_url":"https://ixigua.com/group/6652300003555410440/","source":"爱东营","aothor":{"media_creator_id":6084128027,"media_name":"爱东营","media_url":"https://www.cnblogs.com/c/user/6084128027/"}},{"video_id":"6523111306629743107","title":"浙江省非遗《迎头鬃》","description":"浙江省非遗《迎头鬃》","keywords":"迎头鬃,浙江省","display_url":"https://ixigua.com/group/6523111306629743107/","source":"中国蓝TV","aothor":{"media_creator_id":5768061262,"media_name":"中国蓝TV","media_url":"https://www.cnblogs.com/c/user/5768061262/"}},{"video_id":"6679339532359303693","title":"传承皮影戏，这家人从未言过苦，跟随镜头一起体验非遗技艺","description":"长沙有个皮影戏世家！","keywords":"皮影戏","display_url":"https://ixigua.com/group/6679339532359303693/","source":"芒果都市","aothor":{"media_creator_id":57373277532,"media_name":"芒果都市","media_url":"https://www.cnblogs.com/c/user/57373277532/"}},{"video_id":"6647662071318053384","title":"非遗地图 寻找身边非遗 满绣","description":"富贵的“皇家刺绣”","keywords":"地图,非遗","display_url":"https://ixigua.com/group/6647662071318053384/","source":"时代记忆文化","aothor":{"media_creator_id":67594022411,"media_name":"时代记忆文化","media_url":"https://www.cnblogs.com/c/user/67594022411/"}},{"video_id":"6569094647245701645","title":"非遗《种子画》","description":"非遗 种子画","keywords":"","display_url":"https://ixigua.com/group/6569094647245701645/","source":"百姓大舞台全民娱乐","aothor":{"media_creator_id":57054740602,"media_name":"百姓大舞台全民娱乐","media_url":"https://www.cnblogs.com/c/user/57054740602/"}}]